txtmsg_rshweet/__init__.py
txtmsg_rshweet/emailmsg.py
txtmsg_rshweet/exceptions.py
txtmsg_rshweet/providers.py
txtmsg_rshweet/txtmsg.py
txtmsg_rshweet-0.0.3.dist-info/METADATA
txtmsg_rshweet-0.0.3.dist-info/WHEEL
txtmsg_rshweet-0.0.3.dist-info/top_level.txt
txtmsg_rshweet-0.0.3.dist-info/RECORD
