Metadata-Version: 2.1
Name: txtmsg-rshweet
Version: 0.0.3
Summary: Generic email and text messaging package
Author: Robert Bunnell
Author-email: <rshweet@gmail.com>
Keywords: python,first package,txtmsg,email
Classifier: Development Status :: 3 - Alpha
Classifier: Intended Audience :: Education
Classifier: Programming Language :: Python :: 2
Classifier: Programming Language :: Python :: 3
Classifier: Operating System :: MacOS :: MacOS X
Classifier: Operating System :: Microsoft :: Windows
